DESCRIPTION.rst
LICENSE
MANIFEST.in
README.rst
setup.py
ligament/__init__.py
ligament/buildcontext.py
ligament/buildcontextfseventhandler.py
ligament/buildtarget.py
ligament/compositors.py
ligament/exceptions.py
ligament/helpers.py
ligament/ligament.py
ligament.egg-info/PKG-INFO
ligament.egg-info/SOURCES.txt
ligament.egg-info/dependency_links.txt
ligament.egg-info/entry_points.txt
ligament.egg-info/requires.txt
ligament.egg-info/top_level.txt
ligament_fs/__init__.py
ligament_precompiler_template/__init__.py