Metadata-Version: 1.1
Name: ligament
Version: 0.0.5.dev
Summary: A grunt-like build system for python
Home-page: http://github.com/Adjective-Object/ligament
Author: Adjective-Object
Author-email: mhuan13@gmail.com
License: Apache 2
Keywords: ligament grunt build automation
Platform: UNKNOWN
Classifier: Development Status :: 3 - Alpha
Classifier: Intended Audience :: Developers
Classifier: Topic :: Software Development :: Build Tools
Classifier: License :: OSI Approved :: Apache Software License
Classifier: Programming Language :: Python :: 2.7
